pdsf/__init__.py
pdsf/sflake.py
pdsf/util.py
pdsf-0.1.9.dist-info/LICENSE.txt
pdsf-0.1.9.dist-info/METADATA
pdsf-0.1.9.dist-info/WHEEL
pdsf-0.1.9.dist-info/top_level.txt
pdsf-0.1.9.dist-info/RECORD
